chunkypandas/__init__.py
chunkypandas/version.py
chunkypandas/core/__init__.py
chunkypandas/core/base.py
chunkypandas/core/dataframe.py
chunkypandas/core/series.py
chunkypandas/utilities/__init__.py
chunkypandas/utilities/utilities.py
chunkypandas-0.0.0.dist-info/METADATA
chunkypandas-0.0.0.dist-info/WHEEL
chunkypandas-0.0.0.dist-info/top_level.txt
chunkypandas-0.0.0.dist-info/zip-safe
chunkypandas-0.0.0.dist-info/RECORD
