Metadata-Version: 2.1
Name: chunkypandas
Version: 0.0.0
Summary: Place the burden of pandas on your hard-drive instead of memory
Home-page: https://www.lockhartlab.org
Author: C. Lockhart
Author-email: chris@lockhartlab.org
License: UNKNOWN
Platform: UNKNOWN
Requires-Dist: numpy
Requires-Dist: pandas
Requires-Dist: typelike
